{
  "district": "nakhon-si-thammarat",
  "districtTh": "นครศรีธรรมราช",
  "districtEn": "Nakhon Si Thammarat",
  "kind": "province",
  "osmRelationId": 18990065,
  "bbox": [
    8.2470139,
    99.7982125,
    8.603301,
    100.0956017
  ],
  "fetchedAt": "2026-05-31T12:29:30.366Z",
  "count": 84,
  "pois": [
    {
      "id": "osm-n1586071724",
      "osmId": 1586071724,
      "osmType": "node",
      "name": "พิพิธภัณฑสถานแห่งชาติ นครศรีธรรมราช",
      "nameTh": null,
      "lat": 8.4004304,
      "lng": 99.9695593,
      "category": "museum",
      "profile": {
        "outdoorness": 0.05,
        "indoorness": 0.95,
        "shade": 0,
        "covered": 1,
        "rainEnjoyment": 0.65,
        "heatTolerance": 0.9,
        "confidence": 0.7
      },
      "openingHoursRaw": null,
      "tags": {}
    },
    {
      "id": "osm-n1586071740",
      "osmId": 1586071740,
      "osmType": "node",
      "name": "พิพิธภัณฑ์หนังตะลุง สุชาติ ทรัพย์สิน",
      "nameTh": "พิพิธภัณฑ์หนังตะลุง สุชาติ ทรัพย์สิน",
      "lat": 8.4144351,
      "lng": 99.9687551,
      "category": "museum",
      "profile": {
        "outdoorness": 0.05,
        "indoorness": 0.95,
        "shade": 0,
        "covered": 1,
        "rainEnjoyment": 0.65,
        "heatTolerance": 0.9,
        "confidence": 0.7
      },
      "openingHoursRaw": null,
      "tags": {}
    },
    {
      "id": "osm-n1586071745",
      "osmId": 1586071745,
      "osmType": "node",
      "name": "วัดพระมหาธาตุ วรมหาวิหาร",
      "nameTh": "วัดพระมหาธาตุ วรมหาวิหาร",
      "lat": 8.4110907,
      "lng": 99.9664341,
      "category": "temple",
      "profile": {
        "outdoorness": 0.6,
        "indoorness": 0.4,
        "shade": 0.35,
        "covered": 0.45,
        "rainEnjoyment": 0.2,
        "heatTolerance": 0.4,
        "confidence": 0.55
      },
      "openingHoursRaw": null,
      "tags": {}
    },
    {
      "id": "osm-n1586071760",
      "osmId": 1586071760,
      "osmType": "node",
      "name": "ศาลหลักเมือง",
      "nameTh": null,
      "lat": 8.4303819,
      "lng": 99.962178,
      "category": "viewpoint",
      "profile": {
        "outdoorness": 0.95,
        "indoorness": 0.05,
        "shade": 0.05,
        "covered": 0.05,
        "rainEnjoyment": 0.05,
        "heatTolerance": 0.25,
        "confidence": 0.55
      },
      "openingHoursRaw": null,
      "tags": {}
    },
    {
      "id": "osm-n1586071764",
      "osmId": 1586071764,
      "osmType": "node",
      "name": "สวนสาธารณะศรีธรรมาโศกราช",
      "nameTh": "สวนสาธารณะศรีธรรมาโศกราช",
      "lat": 8.427288,
      "lng": 99.9626375,
      "category": "viewpoint",
      "profile": {
        "outdoorness": 0.95,
        "indoorness": 0.05,
        "shade": 0.05,
        "covered": 0.05,
        "rainEnjoyment": 0.05,
        "heatTolerance": 0.25,
        "confidence": 0.55
      },
      "openingHoursRaw": null,
      "tags": {}
    },
    {
      "id": "osm-n1586071772",
      "osmId": 1586071772,
      "osmType": "node",
      "name": "หอพระนารายณ์",
      "nameTh": null,
      "lat": 8.424336,
      "lng": 99.9643086,
      "category": "temple",
      "profile": {
        "outdoorness": 0.6,
        "indoorness": 0.4,
        "shade": 0.35,
        "covered": 0.45,
        "rainEnjoyment": 0.2,
        "heatTolerance": 0.4,
        "confidence": 0.55
      },
      "openingHoursRaw": null,
      "tags": {}
    },
    {
      "id": "osm-n1586071777",
      "osmId": 1586071777,
      "osmType": "node",
      "name": "หอพระอิศวร",
      "nameTh": null,
      "lat": 8.4242893,
      "lng": 99.9638358,
      "category": "temple",
      "profile": {
        "outdoorness": 0.6,
        "indoorness": 0.4,
        "shade": 0.35,
        "covered": 0.45,
        "rainEnjoyment": 0.2,
        "heatTolerance": 0.4,
        "confidence": 0.55
      },
      "openingHoursRaw": null,
      "tags": {}
    },
    {
      "id": "osm-n1662778329",
      "osmId": 1662778329,
      "osmType": "node",
      "name": "มัสยิดซอลาฮุดดีน",
      "nameTh": "มัสยิดซอลาฮุดดีน",
      "lat": 8.4325685,
      "lng": 99.961013,
      "category": "temple",
      "profile": {
        "outdoorness": 0.6,
        "indoorness": 0.4,
        "shade": 0.35,
        "covered": 0.45,
        "rainEnjoyment": 0.2,
        "heatTolerance": 0.4,
        "confidence": 0.55
      },
      "openingHoursRaw": null,
      "tags": {}
    },
    {
      "id": "osm-n1662778511",
      "osmId": 1662778511,
      "osmType": "node",
      "name": "วัดสวนป่าน",
      "nameTh": "วัดสวนป่าน",
      "lat": 8.4175579,
      "lng": 99.9648555,
      "category": "temple",
      "profile": {
        "outdoorness": 0.6,
        "indoorness": 0.4,
        "shade": 0.35,
        "covered": 0.45,
        "rainEnjoyment": 0.2,
        "heatTolerance": 0.4,
        "confidence": 0.55
      },
      "openingHoursRaw": null,
      "tags": {}
    },
    {
      "id": "osm-n2408723635",
      "osmId": 2408723635,
      "osmType": "node",
      "name": "ครัวนายหนัง​",
      "nameTh": null,
      "lat": 8.4216448,
      "lng": 99.9731398,
      "category": "restaurant",
      "profile": {
        "outdoorness": 0.2,
        "indoorness": 0.8,
        "shade": 0.1,
        "covered": 0.85,
        "rainEnjoyment": 0.55,
        "heatTolerance": 0.8,
        "confidence": 0.55
      },
      "openingHoursRaw": null,
      "tags": {}
    },
    {
      "id": "osm-n2408726496",
      "osmId": 2408726496,
      "osmType": "node",
      "name": "Robinson",
      "nameTh": null,
      "lat": 8.4373095,
      "lng": 99.9698997,
      "category": "mall",
      "profile": {
        "outdoorness": 0.02,
        "indoorness": 0.98,
        "shade": 0,
        "covered": 1,
        "rainEnjoyment": 0.5,
        "heatTolerance": 0.95,
        "confidence": 0.7
      },
      "openingHoursRaw": null,
      "tags": {}
    },
    {
      "id": "osm-n2408728842",
      "osmId": 2408728842,
      "osmType": "node",
      "name": "Bovorn Bazar",
      "nameTh": null,
      "lat": 8.4409072,
      "lng": 99.9668741,
      "category": "market",
      "profile": {
        "outdoorness": 0.45,
        "indoorness": 0.55,
        "shade": 0.6,
        "covered": 0.65,
        "rainEnjoyment": 0.35,
        "heatTolerance": 0.45,
        "confidence": 0.5
      },
      "openingHoursRaw": null,
      "tags": {}
    },
    {
      "id": "osm-n2408740768",
      "osmId": 2408740768,
      "osmType": "node",
      "name": "วัดมเหยงคณ",
      "nameTh": null,
      "lat": 8.4340195,
      "lng": 99.9624109,
      "category": "temple",
      "profile": {
        "outdoorness": 0.6,
        "indoorness": 0.4,
        "shade": 0.35,
        "covered": 0.45,
        "rainEnjoyment": 0.2,
        "heatTolerance": 0.4,
        "confidence": 0.55
      },
      "openingHoursRaw": null,
      "tags": {}
    },
    {
      "id": "osm-n2408851431",
      "osmId": 2408851431,
      "osmType": "node",
      "name": "ร้านอาหาร​ บังบ่าว",
      "nameTh": null,
      "lat": 8.440697,
      "lng": 99.9690809,
      "category": "restaurant",
      "profile": {
        "outdoorness": 0.2,
        "indoorness": 0.8,
        "shade": 0.1,
        "covered": 0.85,
        "rainEnjoyment": 0.55,
        "heatTolerance": 0.8,
        "confidence": 0.55
      },
      "openingHoursRaw": "15:00-23:30",
      "tags": {
        "cuisine": "regional;thai"
      }
    },
    {
      "id": "osm-n4144515190",
      "osmId": 4144515190,
      "osmType": "node",
      "name": "Please Bar",
      "nameTh": null,
      "lat": 8.4219147,
      "lng": 99.9721159,
      "category": "bar",
      "profile": {
        "outdoorness": 0.3,
        "indoorness": 0.7,
        "shade": 0.2,
        "covered": 0.7,
        "rainEnjoyment": 0.55,
        "heatTolerance": 0.65,
        "confidence": 0.5
      },
      "openingHoursRaw": null,
      "tags": {}
    },
    {
      "id": "osm-n4237233990",
      "osmId": 4237233990,
      "osmType": "node",
      "name": "Suktawee",
      "nameTh": null,
      "lat": 8.443644,
      "lng": 99.961567,
      "category": "restaurant",
      "profile": {
        "outdoorness": 0.2,
        "indoorness": 0.8,
        "shade": 0.1,
        "covered": 0.85,
        "rainEnjoyment": 0.55,
        "heatTolerance": 0.8,
        "confidence": 0.55
      },
      "openingHoursRaw": "Mo-Sa 10:30-21:00",
      "tags": {
        "cuisine": "chinese"
      }
    },
    {
      "id": "osm-n4285933891",
      "osmId": 4285933891,
      "osmType": "node",
      "name": "สุขทวีโภชนา",
      "nameTh": "สุขทวีโภชนา",
      "lat": 8.4436374,
      "lng": 99.96152,
      "category": "restaurant",
      "profile": {
        "outdoorness": 0.2,
        "indoorness": 0.8,
        "shade": 0.1,
        "covered": 0.85,
        "rainEnjoyment": 0.55,
        "heatTolerance": 0.8,
        "confidence": 0.55
      },
      "openingHoursRaw": "Mo-Sa 10:30-21:00",
      "tags": {
        "cuisine": "asian;chinese"
      }
    },
    {
      "id": "osm-n4318963691",
      "osmId": 4318963691,
      "osmType": "node",
      "name": "McDonald's",
      "nameTh": null,
      "lat": 8.4272042,
      "lng": 99.9723819,
      "category": "restaurant",
      "profile": {
        "outdoorness": 0.2,
        "indoorness": 0.8,
        "shade": 0.1,
        "covered": 0.85,
        "rainEnjoyment": 0.55,
        "heatTolerance": 0.8,
        "confidence": 0.55
      },
      "openingHoursRaw": "24/7",
      "tags": {
        "cuisine": "burger"
      }
    },
    {
      "id": "osm-n4320666689",
      "osmId": 4320666689,
      "osmType": "node",
      "name": "Jae Fon Padthai",
      "nameTh": null,
      "lat": 8.4411368,
      "lng": 99.9597703,
      "category": "restaurant",
      "profile": {
        "outdoorness": 0.2,
        "indoorness": 0.8,
        "shade": 0.1,
        "covered": 0.85,
        "rainEnjoyment": 0.55,
        "heatTolerance": 0.8,
        "confidence": 0.55
      },
      "openingHoursRaw": "Mo-Su 10:00-16:00",
      "tags": {}
    },
    {
      "id": "osm-n4851295228",
      "osmId": 4851295228,
      "osmType": "node",
      "name": "VR 604 Bo Ang",
      "nameTh": "VR 604",
      "lat": 8.4383115,
      "lng": 99.9672857,
      "category": "restaurant",
      "profile": {
        "outdoorness": 0.2,
        "indoorness": 0.8,
        "shade": 0.1,
        "covered": 0.85,
        "rainEnjoyment": 0.55,
        "heatTolerance": 0.8,
        "confidence": 0.55
      },
      "openingHoursRaw": "Mo-Sa 07:00-15:00",
      "tags": {}
    },
    {
      "id": "osm-n5073559023",
      "osmId": 5073559023,
      "osmType": "node",
      "name": "VR 604 BKT",
      "nameTh": "VR 604",
      "lat": 8.4209243,
      "lng": 99.9646876,
      "category": "restaurant",
      "profile": {
        "outdoorness": 0.2,
        "indoorness": 0.8,
        "shade": 0.1,
        "covered": 0.85,
        "rainEnjoyment": 0.55,
        "heatTolerance": 0.8,
        "confidence": 0.55
      },
      "openingHoursRaw": "Mo-Fr 09:00-18:00",
      "tags": {}
    },
    {
      "id": "osm-n5073617223",
      "osmId": 5073617223,
      "osmType": "node",
      "name": "604 Bakuteh",
      "nameTh": "604 Bakuteh",
      "lat": 8.420432,
      "lng": 99.9643701,
      "category": "restaurant",
      "profile": {
        "outdoorness": 0.2,
        "indoorness": 0.8,
        "shade": 0.1,
        "covered": 0.85,
        "rainEnjoyment": 0.55,
        "heatTolerance": 0.8,
        "confidence": 0.55
      },
      "openingHoursRaw": null,
      "tags": {}
    },
    {
      "id": "osm-n5532434221",
      "osmId": 5532434221,
      "osmType": "node",
      "name": "nude",
      "nameTh": null,
      "lat": 8.484895,
      "lng": 100.0463587,
      "category": "bar",
      "profile": {
        "outdoorness": 0.3,
        "indoorness": 0.7,
        "shade": 0.2,
        "covered": 0.7,
        "rainEnjoyment": 0.55,
        "heatTolerance": 0.65,
        "confidence": 0.5
      },
      "openingHoursRaw": null,
      "tags": {}
    },
    {
      "id": "osm-n5745256521",
      "osmId": 5745256521,
      "osmType": "node",
      "name": "กัปตัน ซีฟู้ด",
      "nameTh": null,
      "lat": 8.44129,
      "lng": 99.9731898,
      "category": "restaurant",
      "profile": {
        "outdoorness": 0.2,
        "indoorness": 0.8,
        "shade": 0.1,
        "covered": 0.85,
        "rainEnjoyment": 0.55,
        "heatTolerance": 0.8,
        "confidence": 0.55
      },
      "openingHoursRaw": null,
      "tags": {}
    },
    {
      "id": "osm-n5746148621",
      "osmId": 5746148621,
      "osmType": "node",
      "name": "โกปี๊",
      "nameTh": null,
      "lat": 8.420421,
      "lng": 99.9637879,
      "category": "restaurant",
      "profile": {
        "outdoorness": 0.2,
        "indoorness": 0.8,
        "shade": 0.1,
        "covered": 0.85,
        "rainEnjoyment": 0.55,
        "heatTolerance": 0.8,
        "confidence": 0.55
      },
      "openingHoursRaw": null,
      "tags": {}
    },
    {
      "id": "osm-n5748389921",
      "osmId": 5748389921,
      "osmType": "node",
      "name": "ร้านใบตอง",
      "nameTh": null,
      "lat": 8.4162902,
      "lng": 99.9649737,
      "category": "restaurant",
      "profile": {
        "outdoorness": 0.2,
        "indoorness": 0.8,
        "shade": 0.1,
        "covered": 0.85,
        "rainEnjoyment": 0.55,
        "heatTolerance": 0.8,
        "confidence": 0.55
      },
      "openingHoursRaw": null,
      "tags": {}
    },
    {
      "id": "osm-n5748390121",
      "osmId": 5748390121,
      "osmType": "node",
      "name": "Pixzel Caffe",
      "nameTh": null,
      "lat": 8.41277,
      "lng": 99.9668246,
      "category": "cafe",
      "profile": {
        "outdoorness": 0.15,
        "indoorness": 0.85,
        "shade": 0.1,
        "covered": 0.9,
        "rainEnjoyment": 0.75,
        "heatTolerance": 0.85,
        "confidence": 0.6
      },
      "openingHoursRaw": null,
      "tags": {}
    },
    {
      "id": "osm-n6402024686",
      "osmId": 6402024686,
      "osmType": "node",
      "name": "ดไพศาลสถิตย์",
      "nameTh": null,
      "lat": 8.5932857,
      "lng": 99.9557743,
      "category": "temple",
      "profile": {
        "outdoorness": 0.6,
        "indoorness": 0.4,
        "shade": 0.35,
        "covered": 0.45,
        "rainEnjoyment": 0.2,
        "heatTolerance": 0.4,
        "confidence": 0.55
      },
      "openingHoursRaw": null,
      "tags": {}
    },
    {
      "id": "osm-n6711326985",
      "osmId": 6711326985,
      "osmType": "node",
      "name": "มากันต้า",
      "nameTh": null,
      "lat": 8.3880497,
      "lng": 99.971041,
      "category": "cafe",
      "profile": {
        "outdoorness": 0.15,
        "indoorness": 0.85,
        "shade": 0.1,
        "covered": 0.9,
        "rainEnjoyment": 0.75,
        "heatTolerance": 0.85,
        "confidence": 0.6
      },
      "openingHoursRaw": null,
      "tags": {}
    },
    {
      "id": "osm-n6711326986",
      "osmId": 6711326986,
      "osmType": "node",
      "name": "ศูนย์อาหารราชดำเนิน",
      "nameTh": null,
      "lat": 8.3881389,
      "lng": 99.9709852,
      "category": "restaurant",
      "profile": {
        "outdoorness": 0.2,
        "indoorness": 0.8,
        "shade": 0.1,
        "covered": 0.85,
        "rainEnjoyment": 0.55,
        "heatTolerance": 0.8,
        "confidence": 0.55
      },
      "openingHoursRaw": null,
      "tags": {}
    },
    {
      "id": "osm-n7244321950",
      "osmId": 7244321950,
      "osmType": "node",
      "name": "สับปะรดสีสะพานยาว",
      "nameTh": null,
      "lat": 8.4428383,
      "lng": 99.9498444,
      "category": "park",
      "profile": {
        "outdoorness": 0.95,
        "indoorness": 0.05,
        "shade": 0.4,
        "covered": 0.05,
        "rainEnjoyment": 0.05,
        "heatTolerance": 0.3,
        "confidence": 0.6
      },
      "openingHoursRaw": "07.00-18.00น.",
      "tags": {}
    },
    {
      "id": "osm-n8156928722",
      "osmId": 8156928722,
      "osmType": "node",
      "name": "อาหารเจ จานเจ",
      "nameTh": null,
      "lat": 8.4367806,
      "lng": 99.968053,
      "category": "restaurant",
      "profile": {
        "outdoorness": 0.2,
        "indoorness": 0.8,
        "shade": 0.1,
        "covered": 0.85,
        "rainEnjoyment": 0.55,
        "heatTolerance": 0.8,
        "confidence": 0.55
      },
      "openingHoursRaw": "Mo-Fr 07:00-15:30",
      "tags": {
        "cuisine": "อาหารเจ/มังสวิรัติ"
      }
    },
    {
      "id": "osm-n8181616726",
      "osmId": 8181616726,
      "osmType": "node",
      "name": "5 field Artillery regiment",
      "nameTh": null,
      "lat": 8.5098688,
      "lng": 99.9527588,
      "category": "temple",
      "profile": {
        "outdoorness": 0.6,
        "indoorness": 0.4,
        "shade": 0.35,
        "covered": 0.45,
        "rainEnjoyment": 0.2,
        "heatTolerance": 0.4,
        "confidence": 0.55
      },
      "openingHoursRaw": null,
      "tags": {}
    },
    {
      "id": "osm-n8261800151",
      "osmId": 8261800151,
      "osmType": "node",
      "name": "วัดราษฏร์ประดิษฐ์",
      "nameTh": null,
      "lat": 8.3960259,
      "lng": 99.945021,
      "category": "temple",
      "profile": {
        "outdoorness": 0.6,
        "indoorness": 0.4,
        "shade": 0.35,
        "covered": 0.45,
        "rainEnjoyment": 0.2,
        "heatTolerance": 0.4,
        "confidence": 0.55
      },
      "openingHoursRaw": null,
      "tags": {}
    },
    {
      "id": "osm-n8439737100",
      "osmId": 8439737100,
      "osmType": "node",
      "name": "ขนมจีนในสวน",
      "nameTh": null,
      "lat": 8.4343353,
      "lng": 99.9330619,
      "category": "restaurant",
      "profile": {
        "outdoorness": 0.4,
        "indoorness": 0.8,
        "shade": 0.2,
        "covered": 0.85,
        "rainEnjoyment": 0.55,
        "heatTolerance": 0.8,
        "confidence": 0.55
      },
      "openingHoursRaw": "Mo-Sa 08:00-14:00",
      "tags": {
        "outdoor_seating": "yes"
      }
    },
    {
      "id": "osm-n8439855526",
      "osmId": 8439855526,
      "osmType": "node",
      "name": "Cafe D'Oro",
      "nameTh": null,
      "lat": 8.4177109,
      "lng": 99.9216601,
      "category": "cafe",
      "profile": {
        "outdoorness": 0.15,
        "indoorness": 0.85,
        "shade": 0.1,
        "covered": 0.9,
        "rainEnjoyment": 0.75,
        "heatTolerance": 0.85,
        "confidence": 0.6
      },
      "openingHoursRaw": null,
      "tags": {}
    },
    {
      "id": "osm-n8763079610",
      "osmId": 8763079610,
      "osmType": "node",
      "name": "โรตีคลาสสิค ถนนเทวบุรี",
      "nameTh": null,
      "lat": 8.4191242,
      "lng": 99.954069,
      "category": "cafe",
      "profile": {
        "outdoorness": 0.35,
        "indoorness": 0.85,
        "shade": 0.2,
        "covered": 0.9,
        "rainEnjoyment": 0.75,
        "heatTolerance": 0.85,
        "confidence": 0.6
      },
      "openingHoursRaw": null,
      "tags": {
        "outdoor_seating": "yes"
      }
    },
    {
      "id": "osm-n9030252297",
      "osmId": 9030252297,
      "osmType": "node",
      "name": "โบสถ",
      "nameTh": null,
      "lat": 8.4105158,
      "lng": 99.8747766,
      "category": "temple",
      "profile": {
        "outdoorness": 0.6,
        "indoorness": 0.4,
        "shade": 0.35,
        "covered": 0.45,
        "rainEnjoyment": 0.2,
        "heatTolerance": 0.4,
        "confidence": 0.55
      },
      "openingHoursRaw": null,
      "tags": {}
    },
    {
      "id": "osm-n9030252306",
      "osmId": 9030252306,
      "osmType": "node",
      "name": "อาคารปฏิบัติธรรม 1",
      "nameTh": "ปฏิบัติธรรม1",
      "lat": 8.4108151,
      "lng": 99.8748066,
      "category": "temple",
      "profile": {
        "outdoorness": 0.6,
        "indoorness": 0.4,
        "shade": 0.35,
        "covered": 0.45,
        "rainEnjoyment": 0.2,
        "heatTolerance": 0.4,
        "confidence": 0.55
      },
      "openingHoursRaw": null,
      "tags": {}
    },
    {
      "id": "osm-n9030255818",
      "osmId": 9030255818,
      "osmType": "node",
      "name": "อาคารปฏิบัติธรรม 2",
      "nameTh": null,
      "lat": 8.4109042,
      "lng": 99.8743968,
      "category": "temple",
      "profile": {
        "outdoorness": 0.6,
        "indoorness": 0.4,
        "shade": 0.35,
        "covered": 0.45,
        "rainEnjoyment": 0.2,
        "heatTolerance": 0.4,
        "confidence": 0.55
      },
      "openingHoursRaw": null,
      "tags": {}
    },
    {
      "id": "osm-n9030255850",
      "osmId": 9030255850,
      "osmType": "node",
      "name": "อาคารปฏิบัติธรรม 4",
      "nameTh": null,
      "lat": 8.4103529,
      "lng": 99.8748326,
      "category": "temple",
      "profile": {
        "outdoorness": 0.6,
        "indoorness": 0.4,
        "shade": 0.35,
        "covered": 0.45,
        "rainEnjoyment": 0.2,
        "heatTolerance": 0.4,
        "confidence": 0.55
      },
      "openingHoursRaw": null,
      "tags": {}
    },
    {
      "id": "osm-n9031267497",
      "osmId": 9031267497,
      "osmType": "node",
      "name": "Market",
      "nameTh": "ตลาดพุธ",
      "lat": 8.3918622,
      "lng": 99.8735056,
      "category": "market",
      "profile": {
        "outdoorness": 0.45,
        "indoorness": 0.55,
        "shade": 0.6,
        "covered": 0.65,
        "rainEnjoyment": 0.35,
        "heatTolerance": 0.45,
        "confidence": 0.5
      },
      "openingHoursRaw": null,
      "tags": {}
    },
    {
      "id": "osm-n9873741175",
      "osmId": 9873741175,
      "osmType": "node",
      "name": "ยงคัง",
      "nameTh": null,
      "lat": 8.4441799,
      "lng": 99.9619198,
      "category": "restaurant",
      "profile": {
        "outdoorness": 0.2,
        "indoorness": 0.8,
        "shade": 0.1,
        "covered": 0.85,
        "rainEnjoyment": 0.55,
        "heatTolerance": 0.8,
        "confidence": 0.55
      },
      "openingHoursRaw": null,
      "tags": {}
    },
    {
      "id": "osm-n11212240058",
      "osmId": 11212240058,
      "osmType": "node",
      "name": "บ้านท่านขุน",
      "nameTh": null,
      "lat": 8.4096136,
      "lng": 99.9675931,
      "category": "viewpoint",
      "profile": {
        "outdoorness": 0.95,
        "indoorness": 0.05,
        "shade": 0.05,
        "covered": 0.05,
        "rainEnjoyment": 0.05,
        "heatTolerance": 0.25,
        "confidence": 0.55
      },
      "openingHoursRaw": null,
      "tags": {}
    },
    {
      "id": "osm-n12260484567",
      "osmId": 12260484567,
      "osmType": "node",
      "name": "ยันหว่าง ณ นคร",
      "nameTh": null,
      "lat": 8.4070653,
      "lng": 99.9762759,
      "category": "restaurant",
      "profile": {
        "outdoorness": 0.2,
        "indoorness": 0.8,
        "shade": 0.1,
        "covered": 0.85,
        "rainEnjoyment": 0.55,
        "heatTolerance": 0.8,
        "confidence": 0.55
      },
      "openingHoursRaw": "24/7",
      "tags": {}
    },
    {
      "id": "osm-n12880885594",
      "osmId": 12880885594,
      "osmType": "node",
      "name": "Rouge - รูจ",
      "nameTh": null,
      "lat": 8.4370927,
      "lng": 99.9694758,
      "category": "bar",
      "profile": {
        "outdoorness": 0.3,
        "indoorness": 0.7,
        "shade": 0.2,
        "covered": 0.7,
        "rainEnjoyment": 0.55,
        "heatTolerance": 0.65,
        "confidence": 0.5
      },
      "openingHoursRaw": "Mo-Su 18:00-00:00",
      "tags": {}
    },
    {
      "id": "osm-n13251970078",
      "osmId": 13251970078,
      "osmType": "node",
      "name": "สำนักสงฆ์วิสุทธิธรรม",
      "nameTh": null,
      "lat": 8.3753906,
      "lng": 99.9770493,
      "category": "temple",
      "profile": {
        "outdoorness": 0.6,
        "indoorness": 0.4,
        "shade": 0.35,
        "covered": 0.45,
        "rainEnjoyment": 0.2,
        "heatTolerance": 0.4,
        "confidence": 0.55
      },
      "openingHoursRaw": null,
      "tags": {}
    },
    {
      "id": "osm-n13251970092",
      "osmId": 13251970092,
      "osmType": "node",
      "name": "ตลาดสดศาลามีชัย",
      "nameTh": null,
      "lat": 8.3811776,
      "lng": 99.973647,
      "category": "market",
      "profile": {
        "outdoorness": 0.45,
        "indoorness": 0.55,
        "shade": 0.6,
        "covered": 0.65,
        "rainEnjoyment": 0.35,
        "heatTolerance": 0.45,
        "confidence": 0.5
      },
      "openingHoursRaw": null,
      "tags": {}
    },
    {
      "id": "osm-n13251970149",
      "osmId": 13251970149,
      "osmType": "node",
      "name": "วัดศาลามีชัย",
      "nameTh": null,
      "lat": 8.3829705,
      "lng": 99.9716739,
      "category": "temple",
      "profile": {
        "outdoorness": 0.6,
        "indoorness": 0.4,
        "shade": 0.35,
        "covered": 0.45,
        "rainEnjoyment": 0.2,
        "heatTolerance": 0.4,
        "confidence": 0.55
      },
      "openingHoursRaw": null,
      "tags": {}
    },
    {
      "id": "osm-n13256160567",
      "osmId": 13256160567,
      "osmType": "node",
      "name": "วัดพระเขียน",
      "nameTh": null,
      "lat": 8.3909811,
      "lng": 99.9258836,
      "category": "temple",
      "profile": {
        "outdoorness": 0.6,
        "indoorness": 0.4,
        "shade": 0.35,
        "covered": 0.45,
        "rainEnjoyment": 0.2,
        "heatTolerance": 0.4,
        "confidence": 0.55
      },
      "openingHoursRaw": null,
      "tags": {}
    },
    {
      "id": "osm-n13256160568",
      "osmId": 13256160568,
      "osmType": "node",
      "name": "วัดนํ้ารอบ",
      "nameTh": null,
      "lat": 8.3930796,
      "lng": 99.9230312,
      "category": "temple",
      "profile": {
        "outdoorness": 0.6,
        "indoorness": 0.4,
        "shade": 0.35,
        "covered": 0.45,
        "rainEnjoyment": 0.2,
        "heatTolerance": 0.4,
        "confidence": 0.55
      },
      "openingHoursRaw": null,
      "tags": {}
    },
    {
      "id": "osm-n13256160569",
      "osmId": 13256160569,
      "osmType": "node",
      "name": "วัดสนธิ์(นาสน)",
      "nameTh": null,
      "lat": 8.3933864,
      "lng": 99.9559125,
      "category": "temple",
      "profile": {
        "outdoorness": 0.6,
        "indoorness": 0.4,
        "shade": 0.35,
        "covered": 0.45,
        "rainEnjoyment": 0.2,
        "heatTolerance": 0.4,
        "confidence": 0.55
      },
      "openingHoursRaw": null,
      "tags": {}
    },
    {
      "id": "osm-n13256160570",
      "osmId": 13256160570,
      "osmType": "node",
      "name": "วัดเตาปูน",
      "nameTh": null,
      "lat": 8.3953897,
      "lng": 99.9572717,
      "category": "temple",
      "profile": {
        "outdoorness": 0.6,
        "indoorness": 0.4,
        "shade": 0.35,
        "covered": 0.45,
        "rainEnjoyment": 0.2,
        "heatTolerance": 0.4,
        "confidence": 0.55
      },
      "openingHoursRaw": null,
      "tags": {}
    },
    {
      "id": "osm-n13261648641",
      "osmId": 13261648641,
      "osmType": "node",
      "name": "วัดวนาราม",
      "nameTh": null,
      "lat": 8.4298128,
      "lng": 99.9089591,
      "category": "temple",
      "profile": {
        "outdoorness": 0.6,
        "indoorness": 0.4,
        "shade": 0.35,
        "covered": 0.45,
        "rainEnjoyment": 0.2,
        "heatTolerance": 0.4,
        "confidence": 0.55
      },
      "openingHoursRaw": null,
      "tags": {}
    },
    {
      "id": "osm-n13261648642",
      "osmId": 13261648642,
      "osmType": "node",
      "name": "วัดโพธิ์เสด็จ",
      "nameTh": null,
      "lat": 8.4162183,
      "lng": 99.9484891,
      "category": "temple",
      "profile": {
        "outdoorness": 0.6,
        "indoorness": 0.4,
        "shade": 0.35,
        "covered": 0.45,
        "rainEnjoyment": 0.2,
        "heatTolerance": 0.4,
        "confidence": 0.55
      },
      "openingHoursRaw": null,
      "tags": {}
    },
    {
      "id": "osm-n13261648643",
      "osmId": 13261648643,
      "osmType": "node",
      "name": "วัดทุ่งแย้",
      "nameTh": null,
      "lat": 8.4101639,
      "lng": 99.9327888,
      "category": "temple",
      "profile": {
        "outdoorness": 0.6,
        "indoorness": 0.4,
        "shade": 0.35,
        "covered": 0.45,
        "rainEnjoyment": 0.2,
        "heatTolerance": 0.4,
        "confidence": 0.55
      },
      "openingHoursRaw": null,
      "tags": {}
    },
    {
      "id": "osm-n13789172055",
      "osmId": 13789172055,
      "osmType": "node",
      "name": "วัดวังตะวันออก",
      "nameTh": null,
      "lat": 8.4379154,
      "lng": 99.9630994,
      "category": "temple",
      "profile": {
        "outdoorness": 0.6,
        "indoorness": 0.4,
        "shade": 0.35,
        "covered": 0.45,
        "rainEnjoyment": 0.2,
        "heatTolerance": 0.4,
        "confidence": 0.55
      },
      "openingHoursRaw": null,
      "tags": {}
    },
    {
      "id": "osm-n13789172056",
      "osmId": 13789172056,
      "osmType": "node",
      "name": "วัดวังตะวันตก",
      "nameTh": null,
      "lat": 8.4380193,
      "lng": 99.9618788,
      "category": "temple",
      "profile": {
        "outdoorness": 0.6,
        "indoorness": 0.4,
        "shade": 0.35,
        "covered": 0.45,
        "rainEnjoyment": 0.2,
        "heatTolerance": 0.4,
        "confidence": 0.55
      },
      "openingHoursRaw": null,
      "tags": {}
    },
    {
      "id": "osm-w314086767",
      "osmId": 314086767,
      "osmType": "way",
      "name": "Cafeteria",
      "nameTh": null,
      "lat": 8.368044,
      "lng": 100.0435755,
      "category": "cafe",
      "profile": {
        "outdoorness": 0.15,
        "indoorness": 0.85,
        "shade": 0.1,
        "covered": 0.9,
        "rainEnjoyment": 0.75,
        "heatTolerance": 0.85,
        "confidence": 0.6
      },
      "openingHoursRaw": "0630 - 1900",
      "tags": {
        "cuisine": "regional"
      }
    },
    {
      "id": "osm-w320648803",
      "osmId": 320648803,
      "osmType": "way",
      "name": "หอสมุด",
      "nameTh": null,
      "lat": 8.3681572,
      "lng": 100.0439812,
      "category": "library",
      "profile": {
        "outdoorness": 0.02,
        "indoorness": 0.98,
        "shade": 0,
        "covered": 1,
        "rainEnjoyment": 0.7,
        "heatTolerance": 0.9,
        "confidence": 0.75
      },
      "openingHoursRaw": "0830 - 2000",
      "tags": {}
    },
    {
      "id": "osm-w554299682",
      "osmId": 554299682,
      "osmType": "way",
      "name": "สวนศรีธรรมโศกราช",
      "nameTh": null,
      "lat": 8.4269472,
      "lng": 99.9625397,
      "category": "park",
      "profile": {
        "outdoorness": 0.95,
        "indoorness": 0.05,
        "shade": 0.4,
        "covered": 0.05,
        "rainEnjoyment": 0.05,
        "heatTolerance": 0.3,
        "confidence": 0.6
      },
      "openingHoursRaw": null,
      "tags": {}
    },
    {
      "id": "osm-w554300469",
      "osmId": 554300469,
      "osmType": "way",
      "name": "สวนเจ้าพระยานคร",
      "nameTh": null,
      "lat": 8.4183733,
      "lng": 99.9644009,
      "category": "park",
      "profile": {
        "outdoorness": 0.95,
        "indoorness": 0.05,
        "shade": 0.4,
        "covered": 0.05,
        "rainEnjoyment": 0.05,
        "heatTolerance": 0.3,
        "confidence": 0.6
      },
      "openingHoursRaw": null,
      "tags": {}
    },
    {
      "id": "osm-w555248885",
      "osmId": 555248885,
      "osmType": "way",
      "name": "สนามหน้าเมือง",
      "nameTh": null,
      "lat": 8.4292234,
      "lng": 99.9625338,
      "category": "park",
      "profile": {
        "outdoorness": 0.95,
        "indoorness": 0.05,
        "shade": 0.4,
        "covered": 0.05,
        "rainEnjoyment": 0.05,
        "heatTolerance": 0.3,
        "confidence": 0.6
      },
      "openingHoursRaw": null,
      "tags": {}
    },
    {
      "id": "osm-w765955692",
      "osmId": 765955692,
      "osmType": "way",
      "name": "วัดสวนหลวง",
      "nameTh": "วัดสวนหลวง",
      "lat": 8.4002216,
      "lng": 99.9683656,
      "category": "temple",
      "profile": {
        "outdoorness": 0.6,
        "indoorness": 0.4,
        "shade": 0.35,
        "covered": 0.45,
        "rainEnjoyment": 0.2,
        "heatTolerance": 0.4,
        "confidence": 0.55
      },
      "openingHoursRaw": null,
      "tags": {}
    },
    {
      "id": "osm-w765955693",
      "osmId": 765955693,
      "osmType": "way",
      "name": "วัดเพชรจริก",
      "nameTh": "วัดเพชรจริก",
      "lat": 8.3975594,
      "lng": 99.9690468,
      "category": "temple",
      "profile": {
        "outdoorness": 0.6,
        "indoorness": 0.4,
        "shade": 0.35,
        "covered": 0.45,
        "rainEnjoyment": 0.2,
        "heatTolerance": 0.4,
        "confidence": 0.55
      },
      "openingHoursRaw": null,
      "tags": {}
    },
    {
      "id": "osm-w766207840",
      "osmId": 766207840,
      "osmType": "way",
      "name": "วัดสระเรียง เมืองนครศรีธรรมราช",
      "nameTh": null,
      "lat": 8.4134624,
      "lng": 99.9668274,
      "category": "temple",
      "profile": {
        "outdoorness": 0.6,
        "indoorness": 0.4,
        "shade": 0.35,
        "covered": 0.45,
        "rainEnjoyment": 0.2,
        "heatTolerance": 0.4,
        "confidence": 0.55
      },
      "openingHoursRaw": null,
      "tags": {}
    },
    {
      "id": "osm-w774940103",
      "osmId": 774940103,
      "osmType": "way",
      "name": "วัดท้าวโคตร",
      "nameTh": "วัดท้าวโคตร",
      "lat": 8.4049823,
      "lng": 99.9675337,
      "category": "temple",
      "profile": {
        "outdoorness": 0.6,
        "indoorness": 0.4,
        "shade": 0.35,
        "covered": 0.45,
        "rainEnjoyment": 0.2,
        "heatTolerance": 0.4,
        "confidence": 0.55
      },
      "openingHoursRaw": null,
      "tags": {}
    },
    {
      "id": "osm-w779267505",
      "osmId": 779267505,
      "osmType": "way",
      "name": "วัดหัวอิฐ",
      "nameTh": null,
      "lat": 8.4311764,
      "lng": 99.9540611,
      "category": "temple",
      "profile": {
        "outdoorness": 0.6,
        "indoorness": 0.4,
        "shade": 0.35,
        "covered": 0.45,
        "rainEnjoyment": 0.2,
        "heatTolerance": 0.4,
        "confidence": 0.55
      },
      "openingHoursRaw": null,
      "tags": {}
    },
    {
      "id": "osm-w975860597",
      "osmId": 975860597,
      "osmType": "way",
      "name": "โบสถ์",
      "nameTh": null,
      "lat": 8.4105092,
      "lng": 99.874751,
      "category": "temple",
      "profile": {
        "outdoorness": 0.6,
        "indoorness": 0.4,
        "shade": 0.35,
        "covered": 0.45,
        "rainEnjoyment": 0.2,
        "heatTolerance": 0.4,
        "confidence": 0.55
      },
      "openingHoursRaw": null,
      "tags": {}
    },
    {
      "id": "osm-w975860598",
      "osmId": 975860598,
      "osmType": "way",
      "name": "วัดสวนพลาราม",
      "nameTh": "วัดสวนพลาราม",
      "lat": 8.410727,
      "lng": 99.8749043,
      "category": "temple",
      "profile": {
        "outdoorness": 0.6,
        "indoorness": 0.4,
        "shade": 0.35,
        "covered": 0.45,
        "rainEnjoyment": 0.2,
        "heatTolerance": 0.4,
        "confidence": 0.55
      },
      "openingHoursRaw": null,
      "tags": {}
    },
    {
      "id": "osm-w975860599",
      "osmId": 975860599,
      "osmType": "way",
      "name": "ปฏิบัติธรรม",
      "nameTh": "ปฏิบัติธรรม",
      "lat": 8.4107821,
      "lng": 99.8747476,
      "category": "temple",
      "profile": {
        "outdoorness": 0.6,
        "indoorness": 0.4,
        "shade": 0.35,
        "covered": 0.45,
        "rainEnjoyment": 0.2,
        "heatTolerance": 0.4,
        "confidence": 0.55
      },
      "openingHoursRaw": null,
      "tags": {}
    },
    {
      "id": "osm-w975860608",
      "osmId": 975860608,
      "osmType": "way",
      "name": "อาคารปฏิบัติธรรม 3",
      "nameTh": null,
      "lat": 8.4103312,
      "lng": 99.8748511,
      "category": "temple",
      "profile": {
        "outdoorness": 0.6,
        "indoorness": 0.4,
        "shade": 0.35,
        "covered": 0.45,
        "rainEnjoyment": 0.2,
        "heatTolerance": 0.4,
        "confidence": 0.55
      },
      "openingHoursRaw": null,
      "tags": {}
    },
    {
      "id": "osm-w1020994858",
      "osmId": 1020994858,
      "osmType": "way",
      "name": "Café Amazon",
      "nameTh": null,
      "lat": 8.5070708,
      "lng": 99.930025,
      "category": "cafe",
      "profile": {
        "outdoorness": 0.15,
        "indoorness": 0.85,
        "shade": 0.1,
        "covered": 0.9,
        "rainEnjoyment": 0.75,
        "heatTolerance": 0.85,
        "confidence": 0.6
      },
      "openingHoursRaw": null,
      "tags": {}
    },
    {
      "id": "osm-w1159032517",
      "osmId": 1159032517,
      "osmType": "way",
      "name": "Robinson Ocean Nakhon Si Thammarat",
      "nameTh": null,
      "lat": 8.4374231,
      "lng": 99.9689048,
      "category": "mall",
      "profile": {
        "outdoorness": 0.02,
        "indoorness": 0.98,
        "shade": 0,
        "covered": 1,
        "rainEnjoyment": 0.5,
        "heatTolerance": 0.95,
        "confidence": 0.7
      },
      "openingHoursRaw": null,
      "tags": {}
    },
    {
      "id": "osm-w1159032518",
      "osmId": 1159032518,
      "osmType": "way",
      "name": "สวนสาธารณะ คูขวาง",
      "nameTh": "สวนสาธารณะ คูขวาง",
      "lat": 8.4377576,
      "lng": 99.970721,
      "category": "park",
      "profile": {
        "outdoorness": 0.95,
        "indoorness": 0.05,
        "shade": 0.4,
        "covered": 0.05,
        "rainEnjoyment": 0.05,
        "heatTolerance": 0.3,
        "confidence": 0.6
      },
      "openingHoursRaw": null,
      "tags": {}
    },
    {
      "id": "osm-w1159032520",
      "osmId": 1159032520,
      "osmType": "way",
      "name": "Ratchaphruek Night Bazaar Market",
      "nameTh": null,
      "lat": 8.4379953,
      "lng": 99.9720022,
      "category": "market",
      "profile": {
        "outdoorness": 0.45,
        "indoorness": 0.55,
        "shade": 0.6,
        "covered": 0.65,
        "rainEnjoyment": 0.35,
        "heatTolerance": 0.45,
        "confidence": 0.5
      },
      "openingHoursRaw": null,
      "tags": {}
    },
    {
      "id": "osm-w1159796944",
      "osmId": 1159796944,
      "osmType": "way",
      "name": "สนามกีฬาองค์การบริหารส่วนจังหวัดนครศรีธรรมราช",
      "nameTh": null,
      "lat": 8.45502,
      "lng": 99.9582308,
      "category": "park",
      "profile": {
        "outdoorness": 0.95,
        "indoorness": 0.05,
        "shade": 0.4,
        "covered": 0.05,
        "rainEnjoyment": 0.05,
        "heatTolerance": 0.3,
        "confidence": 0.6
      },
      "openingHoursRaw": null,
      "tags": {}
    },
    {
      "id": "osm-w1161331473",
      "osmId": 1161331473,
      "osmType": "way",
      "name": "วัดโคกธาตุ",
      "nameTh": null,
      "lat": 8.4058769,
      "lng": 99.9658273,
      "category": "temple",
      "profile": {
        "outdoorness": 0.6,
        "indoorness": 0.4,
        "shade": 0.35,
        "covered": 0.45,
        "rainEnjoyment": 0.2,
        "heatTolerance": 0.4,
        "confidence": 0.55
      },
      "openingHoursRaw": null,
      "tags": {}
    },
    {
      "id": "osm-w1161332938",
      "osmId": 1161332938,
      "osmType": "way",
      "name": "วัดชายนา",
      "nameTh": null,
      "lat": 8.4047018,
      "lng": 99.9660779,
      "category": "temple",
      "profile": {
        "outdoorness": 0.6,
        "indoorness": 0.4,
        "shade": 0.35,
        "covered": 0.45,
        "rainEnjoyment": 0.2,
        "heatTolerance": 0.4,
        "confidence": 0.55
      },
      "openingHoursRaw": null,
      "tags": {}
    },
    {
      "id": "osm-w1161336854",
      "osmId": 1161336854,
      "osmType": "way",
      "name": "สวนหน้าหอพระพุทธสิหงค์",
      "nameTh": null,
      "lat": 8.4191301,
      "lng": 99.9640117,
      "category": "park",
      "profile": {
        "outdoorness": 0.95,
        "indoorness": 0.05,
        "shade": 0.4,
        "covered": 0.05,
        "rainEnjoyment": 0.05,
        "heatTolerance": 0.3,
        "confidence": 0.6
      },
      "openingHoursRaw": null,
      "tags": {}
    },
    {
      "id": "osm-w1161336859",
      "osmId": 1161336859,
      "osmType": "way",
      "name": "ลานหน้าศาลจังหวัด",
      "nameTh": null,
      "lat": 8.4198619,
      "lng": 99.9641278,
      "category": "park",
      "profile": {
        "outdoorness": 0.95,
        "indoorness": 0.05,
        "shade": 0.4,
        "covered": 0.05,
        "rainEnjoyment": 0.05,
        "heatTolerance": 0.3,
        "confidence": 0.6
      },
      "openingHoursRaw": null,
      "tags": {}
    },
    {
      "id": "osm-w1167960085",
      "osmId": 1167960085,
      "osmType": "way",
      "name": "ก๋วยเตี๋ยว เรือแม่สมศรี5",
      "nameTh": null,
      "lat": 8.4723724,
      "lng": 99.9640293,
      "category": "park",
      "profile": {
        "outdoorness": 0.95,
        "indoorness": 0.05,
        "shade": 0.4,
        "covered": 0.05,
        "rainEnjoyment": 0.05,
        "heatTolerance": 0.3,
        "confidence": 0.6
      },
      "openingHoursRaw": null,
      "tags": {}
    },
    {
      "id": "osm-w1351988349",
      "osmId": 1351988349,
      "osmType": "way",
      "name": "Yummy to my Tummy",
      "nameTh": null,
      "lat": 8.4203361,
      "lng": 99.9650025,
      "category": "restaurant",
      "profile": {
        "outdoorness": 0.2,
        "indoorness": 0.8,
        "shade": 0.1,
        "covered": 0.85,
        "rainEnjoyment": 0.55,
        "heatTolerance": 0.8,
        "confidence": 0.55
      },
      "openingHoursRaw": null,
      "tags": {
        "cuisine": "pizza;burger;coffee_shop;american;sandwich;pasta;salad;dessert;western;egional"
      }
    },
    {
      "id": "osm-w1444224415",
      "osmId": 1444224415,
      "osmType": "way",
      "name": "สวนสี่แยกเบญจมฯ",
      "nameTh": null,
      "lat": 8.4339013,
      "lng": 99.921739,
      "category": "park",
      "profile": {
        "outdoorness": 0.95,
        "indoorness": 0.05,
        "shade": 0.4,
        "covered": 0.05,
        "rainEnjoyment": 0.05,
        "heatTolerance": 0.3,
        "confidence": 0.6
      },
      "openingHoursRaw": null,
      "tags": {}
    }
  ]
}